{
  "hash": "e431d09b",
  "configHash": "14199864",
  "lockfileHash": "9f3d48ee",
  "browserHash": "97579014",
  "optimized": {
    "vue": {
      "src": "../../../../node_modules/vue/dist/vue.runtime.esm-bundler.js",
      "file": "vue.js",
      "fileHash": "4def1827",
      "needsInterop": false
    },
    "vitepress > @vue/devtools-api": {
      "src": "../../../../node_modules/@vue/devtools-api/dist/index.js",
      "file": "vitepress___@vue_devtools-api.js",
      "fileHash": "fc68ac63",
      "needsInterop": false
    },
    "vitepress > @vueuse/core": {
      "src": "../../../../node_modules/@vueuse/core/index.mjs",
      "file": "vitepress___@vueuse_core.js",
      "fileHash": "c98bec06",
      "needsInterop": false
    }
  },
  "chunks": {
    "chunk-Y6PV5SQ5": {
      "file": "chunk-Y6PV5SQ5.js"
    }
  }
}